gym_collabsort/__init__.py
gym_collabsort/config.py
gym_collabsort/py.typed
gym_collabsort/board/arm.py
gym_collabsort/board/board.py
gym_collabsort/board/object.py
gym_collabsort/board/sprite.py
gym_collabsort/envs/env.py
gym_collabsort/envs/robot.py
gym_collabsort-0.2.1.dist-info/METADATA
gym_collabsort-0.2.1.dist-info/WHEEL
gym_collabsort-0.2.1.dist-info/licenses/LICENSE
gym_collabsort-0.2.1.dist-info/RECORD
